jldc/__init__.py
jldc/classes.py
jldc/constants.py
jldc/core.py
jldc/py.typed
jldc-0.0.6.dist-info/LICENSE
jldc-0.0.6.dist-info/METADATA
jldc-0.0.6.dist-info/WHEEL
jldc-0.0.6.dist-info/top_level.txt
jldc-0.0.6.dist-info/RECORD
