Metadata-Version: 2.1
Name: jldc
Version: 0.0.6
Summary: Simplify using JSONLines files alongside dataclasses.
Author-email: Lukas Twist <itsluketwist@gmail.com>
License: MIT License
Project-URL: Homepage, https://github.com/itsluketwist/jldc
Project-URL: Code, https://github.com/itsluketwist/jldc
Project-URL: Download, https://github.com/itsluketwist/jldc/tags
Keywords: jldc,jsonlines,dataclasses
Classifier: License :: OSI Approved :: MIT License
Classifier: Programming Language :: Python
Classifier: Programming Language :: Python :: 3
Requires-Python: >=3.10
License-File: LICENSE
Requires-Dist: dacite ~=1.8.1
Provides-Extra: dev
Requires-Dist: pre-commit ; extra == 'dev'
Requires-Dist: pytest ; extra == 'dev'
Provides-Extra: ml
Requires-Dist: numpy ~=1.26.0 ; extra == 'ml'
